deferred/__init__.py
deferred_py-0.0.1.dist-info/METADATA
deferred_py-0.0.1.dist-info/RECORD
deferred_py-0.0.1.dist-info/WHEEL
deferred_py-0.0.1.dist-info/top_level.txt
