Metadata-Version: 2.1
Name: deferred-py
Version: 0.0.1
Summary: A Javascript-style defer() implementation for promises in multi-threaded Python applications.
Home-page: https://github.com/everclear72216/deferred-py
Author: Martin Bertsche
Author-email: martin72216@googlemail.com
License: MIT
Platform: UNKNOWN
Classifier: Development Status :: 4 - Beta
